dry_rest_permissions/__init__.py
dry_rest_permissions/generics.py
dry_rest_permissions/py.typed
django_dry_rest_permissions-1.2.0.dist-info/LICENSE
django_dry_rest_permissions-1.2.0.dist-info/METADATA
django_dry_rest_permissions-1.2.0.dist-info/WHEEL
django_dry_rest_permissions-1.2.0.dist-info/top_level.txt
django_dry_rest_permissions-1.2.0.dist-info/RECORD
