Metadata-Version: 2.1
Name: django-dry-rest-permissions
Version: 1.2.0
Summary: Rules based permissions for the Django Rest Framework
Home-page: https://github.com/FJNR-inc/dry-rest-permissions
Author: FJNR-inc
Author-email: noel.rignon@fjnr.ca
License: BSD
Platform: UNKNOWN
Classifier: Development Status :: 5 - Production/Stable
Classifier: Environment :: Web Environment
Classifier: Framework :: Django
Classifier: Intended Audience :: Developers
Classifier: License :: OSI Approved :: BSD License
Classifier: Operating System :: OS Independent
Classifier: Natural Language :: English
Classifier: Programming Language :: Python :: 3.4
Classifier: Programming Language :: Python :: 3.5
Classifier: Programming Language :: Python :: 3.6
Classifier: Programming Language :: Python :: 3.7
Classifier: Programming Language :: Python :: 3.8
Classifier: Topic :: Internet :: WWW/HTTP
License-File: LICENSE
